aznuke/__init__.py
aznuke/__main__.py
aznuke/_version.py
aznuke/cli.py
aznuke/config/exclusions.yaml
aznuke/core/__init__.py
aznuke/src/__init__.py
aznuke/src/animations.py
aznuke/src/auth.py
aznuke/src/deletion.py
aznuke/src/dependencies.py
aznuke/src/discovery.py
aznuke/src/filtering.py
aznuke/src/safety.py
aznuke-0.1.8.dist-info/licenses/LICENSE
src/__init__.py
src/animations.py
src/auth.py
src/deletion.py
src/dependencies.py
src/discovery.py
src/filtering.py
src/safety.py
aznuke-0.1.8.dist-info/METADATA
aznuke-0.1.8.dist-info/WHEEL
aznuke-0.1.8.dist-info/entry_points.txt
aznuke-0.1.8.dist-info/top_level.txt
aznuke-0.1.8.dist-info/RECORD
