Metadata-Version: 2.4
Name: aznuke
Version: 0.1.8
Summary: Azure resource scanner and cleanup tool
Home-page: https://github.com/sojay/azure-nuke
Author: Samuel Okorie
Author-email: Samuel Okorie <thesamokorie@gmail.com>
License: MIT
Project-URL: Homepage, https://github.com/sojay/azure-nuke
Project-URL: Documentation, https://sojay.github.io/azure-nuke
Project-URL: Repository, https://github.com/sojay/azure-nuke.git
Project-URL: Issues, https://github.com/sojay/azure-nuke/issues
Keywords: azure,cloud,cleanup,infrastructure,devops
Classifier: Development Status :: 4 - Beta
Classifier: Intended Audience :: Developers
Classifier: Intended Audience :: System Administrators
Classifier: License :: OSI Approved :: MIT License
Classifier: Programming Language :: Python :: 3
Classifier: Programming Language :: Python :: 3.8
Classifier: Programming Language :: Python :: 3.9
Classifier: Programming Language :: Python :: 3.10
Classifier: Programming Language :: Python :: 3.11
Classifier: Topic :: System :: Systems Administration
Classifier: Topic :: Utilities
Requires-Python: >=3.8
License-File: LICENSE
Requires-Dist: azure-identity>=1.10.0
Requires-Dist: azure-mgmt-resource>=22.0.0
Requires-Dist: azure-mgmt-subscription>=3.1.1
Requires-Dist: azure-mgmt-compute>=27.0.0
Requires-Dist: azure-mgmt-network>=22.0.0
Requires-Dist: azure-mgmt-storage>=20.0.0
Requires-Dist: azure-mgmt-keyvault>=10.0.0
Requires-Dist: azure-mgmt-monitor>=5.0.0
Requires-Dist: pyyaml>=6.0
Requires-Dist: colorama==0.4.6
Requires-Dist: pyfiglet==0.8.post1
Requires-Dist: tqdm==4.66.1
Dynamic: author
Dynamic: home-page
Dynamic: license-file
Dynamic: requires-python
